BenToTru/__init__.py
BenToTru/btt.py
BenToTru/data/Matrizes Consolidadas (em tep) 1970 - 2022.xls
BenToTru/data/coeficientes_emissoes_gee_ajustado.csv
BenToTru/data/correspondencia_MIP56_TRU51_BEN.csv
BenToTru/data/correspondencia_TRU68_BEN.csv
BenToTru/data/correspondencia_produtos_TRU51_BEN.csv
BenToTru/data/correspondencia_produtos_TRU68_BEN.csv
BenToTru-0.1.0.dist-info/LICENSE
BenToTru-0.1.0.dist-info/METADATA
BenToTru-0.1.0.dist-info/WHEEL
BenToTru-0.1.0.dist-info/top_level.txt
BenToTru-0.1.0.dist-info/RECORD
