Metadata-Version: 2.1
Name: BenToTru
Version: 0.1.0
Summary: Estimation of GHG emissions based on energy consumption in Brazil, broken down by 51 and 68 distinct activities.
Home-page: https://github.com/fms-1988
Author: Felipe Morelli Da Silva
Author-email: fms.morelli@gmail.com
Classifier: Programming Language :: Python :: 3
Classifier: License :: OSI Approved :: MIT License
Classifier: Operating System :: OS Independent
Requires-Python: >=3.7
License-File: LICENSE
Requires-Dist: iotbr (>=0.0.19)
Requires-Dist: numpy
Requires-Dist: pandas
Requires-Dist: xlrd
